idlmav/__init__.py
idlmav/coloring.py
idlmav/idlmav.py
idlmav/layout.py
idlmav/mavdbgutils.py
idlmav/mavoptions.py
idlmav/mavtypes.py
idlmav/mavutils.py
idlmav/merging.py
idlmav/static_viewers.py
idlmav/tracing.py
idlmav/renderers/figure_renderer.py
idlmav/renderers/renderer_utils.py
idlmav/renderers/widget_renderer.py
idlmav-1.1.0.dist-info/LICENSE
idlmav-1.1.0.dist-info/METADATA
idlmav-1.1.0.dist-info/WHEEL
idlmav-1.1.0.dist-info/top_level.txt
idlmav-1.1.0.dist-info/RECORD
