Metadata-Version: 2.2
Name: idlmav
Version: 1.1.0
Summary: Create interactive visualizations of model architectures for display in Jupyter notebooks
Author-email: Dirk Oosthuizen <dirk.jj.oosthuizen@gmail.com>
License: MIT
Project-URL: Repository, https://github.com/d112358/idlmav.git
Project-URL: Bug Tracker, https://github.com/d112358/idlmav/issues
Keywords: pytorch,torch,deep learning,neural network,model architecture,visualization,interactive,jupyter,notebook,plotly
Classifier: License :: OSI Approved :: MIT License
Classifier: Programming Language :: Python
Requires-Python: >=3.9
License-File: LICENSE
Requires-Dist: torch>=2.3.0
Requires-Dist: numpy
Requires-Dist: tabulate
Requires-Dist: munkres
Requires-Dist: plotly
Requires-Dist: nbformat
Requires-Dist: ipywidgets
